pydoc_md/__init__.py
pydoc_md/__main__.py
pydoc_md/generator.py
pydoc_md/parser.py
pydoc_md-0.1.0.dist-info/entry_points.txt
pydoc_md-0.1.0.dist-info/WHEEL
pydoc_md-0.1.0.dist-info/METADATA
pydoc_md-0.1.0.dist-info/RECORD
