Metadata-Version: 2.1
Name: pydoc-md
Version: 0.1.0
Summary: 
License: MIT
Author: Yohei Tamura
Author-email: tamuhey@gmail.com
Requires-Python: >=3.6,<4.0
Classifier: License :: OSI Approved :: MIT License
Classifier: Programming Language :: Python :: 3
Classifier: Programming Language :: Python :: 3.6
Classifier: Programming Language :: Python :: 3.7
Classifier: Programming Language :: Python :: 3.8
Requires-Dist: docstring_parser (>=0.7.2,<0.8.0)
Requires-Dist: fire (>=0.3.1,<0.4.0)
Requires-Dist: loguru (>=0.5.1,<0.6.0)
